xson/__init__.py
xson/dump.py
xson/load.py
xson/pkgdata.py
xson/tool.py
xson-1.1.1.dist-info/licenses/LICENSE.rst
xson-1.1.1.dist-info/METADATA
xson-1.1.1.dist-info/WHEEL
xson-1.1.1.dist-info/entry_points.txt
xson-1.1.1.dist-info/top_level.txt
xson-1.1.1.dist-info/RECORD
